omigo_core/__init__.py
omigo_core/dataframe.py
omigo_core/dataset.py
omigo_core/dfutils.py
omigo_core/funclib.py
omigo_core/graph_traversal.py
omigo_core/llm_funcs.py
omigo_core/s3io_wrapper.py
omigo_core/timefuncs.py
omigo_core/tsv.py
omigo_core/udfs.py
omigo_core/utils.py
omigo_core/wsclient.py
omigo_core-0.9.2.dist-info/METADATA
omigo_core-0.9.2.dist-info/WHEEL
omigo_core-0.9.2.dist-info/top_level.txt
omigo_core-0.9.2.dist-info/RECORD
