Metadata-Version: 2.4
Name: omigo_core
Version: 0.9.2
Summary: Data Analytics Library for Python
Home-page: https://github.com/CrowdStrike/omigo-data-analytics
Author: amit jaiswal
Author-email: amit.jaiswal@gmail.com
Project-URL: Bug Tracker, https://github.com/CrowdStrike/omigo-data-analytics/browse
Classifier: Programming Language :: Python :: 3
Classifier: License :: OSI Approved :: MIT License
Classifier: Operating System :: OS Independent
Requires-Python: >=3.6
Requires-Dist: boto3
Requires-Dist: mmh3
Requires-Dist: numpy
Requires-Dist: pandas
Requires-Dist: statistics
Requires-Dist: requests
Requires-Dist: python-dateutil
Requires-Dist: six
